{"story":{"group_1":[{"autoTurnLast":0.01,"chara":[{"cheek":0,"face":"mtn_ex_030.exp.json","id":100102,"motion":0,"mouthOpen":0,"pos":1}],"turnChangeIn":"fadeIn"},{"bg":"bg_adv_21031.jpg","bgm":"bgm01_anime25","chara":[{"id":100102,"voiceFull":"fullvoice/section_101203/vo_full_101203-3-1"}],"nameCenter":"Iroha","textCenter":"Esperaba que el arcade estuviera lleno@de gente que da miedo, pero...","turnChangeOut":"fadeOut"},{"chara":[{"cheek":0,"id":100102,"mouthOpen":0,"voiceFull":"fullvoice/section_101203/vo_full_101203-3-2","voiceFullStop":"fullvoice/section_101203/vo_full_101203-3-1"}],"textCenter":"Todos aquí se ven muy normales...@Aun así, todo esto es algo abrumador..."},{"chara":[{"cheek":0,"id":100102,"lipSynch":0,"mouthOpen":0,"voiceFull":"fullvoice/section_101203/vo_full_101203-3-3","voiceFullStop":"fullvoice/section_101203/vo_full_101203-3-2"}],"textCenter":"(Rena... Rena...)"},{"chara":[{"cheek":0,"face":"mtn_ex_050.exp.json","id":100102,"lipSynch":1,"motion":401,"mouthOpen":0,"voiceFull":"fullvoice/section_101203/vo_full_101203-3-4","voiceFullStop":"fullvoice/section_101203/vo_full_101203-3-3"}],"textCenter":"[chara:100102:effect_emotion_surprise_0][se:7226_shock]¡¿...?!"},{"chara":[{"cheek":0,"id":100102,"mouthOpen":0,"voiceFull":"fullvoice/section_101203/vo_full_101203-3-5","voiceFullStop":"fullvoice/section_101203/vo_full_101203-3-4"}],"textCenter":"Por ahí..."},{"chara":[{"cheek":0,"face":"mtn_ex_030.exp.json","id":100102,"motion":0,"mouthOpen":0,"voiceFull":"fullvoice/section_101203/vo_full_101203-3-6","voiceFullStop":"fullvoice/section_101203/vo_full_101203-3-5"}],"textCenter":"Podrá ser..."},{"autoTurnLast":0.01,"chara":[{"cheek":1,"face":"mtn_ex_020.exp.json","id":100901,"motion":201,"mouthOpen":0,"pos":1}],"turnChangeIn":"rollInFast"},{"bg":"bg_adv_21031.jpg","chara":[{"id":100901,"voiceFull":"fullvoice/section_101203/vo_full_101203-3-7"}],"nameCenter":"Rena","textCenter":"[chara:100901:effect_emotion_angry_0][se:7219_strain]Ugh, ¡Demonios!@¡¿Qué le pasa a esta máquina?!","turnChangeOut":"rollOutFast"},{"chara":[{"id":100901,"mouthOpen":0,"voiceFull":"fullvoice/section_101203/vo_full_101203-3-8","voiceFullStop":"fullvoice/section_101203/vo_full_101203-3-7"}],"textCenter":"¡Debí obtener un \"GREAT\" no un \"BAD\"!"},{"chara":[{"cheek":1,"face":"mtn_ex_050.exp.json","id":100901,"motion":200,"mouthOpen":0,"voiceFull":"fullvoice/section_101203/vo_full_101203-3-9","voiceFullStop":"fullvoice/section_101203/vo_full_101203-3-8"}],"textCenter":"¡De seguro está rota!"},{"autoTurnLast":0.01,"chara":[{"cheek":0,"face":"mtn_ex_030.exp.json","id":100102,"motion":0,"mouthOpen":0,"pos":1}],"turnChangeIn":"rollInFast","voiceFullStop":"fullvoice/section_101203/vo_full_101203-3-9"},{"bg":"bg_adv_21031.jpg","chara":[{"id":100102,"voiceFull":"fullvoice/section_101203/vo_full_101203-3-10"}],"nameCenter":"Iroha","textCenter":"Ahí esta...","turnChangeOut":"rollOutFast"},{"chara":[{"cheek":0,"id":100102,"lipSynch":0,"motion":301,"mouthOpen":0,"voiceFull":"fullvoice/section_101203/vo_full_101203-3-11","voiceFullStop":"fullvoice/section_101203/vo_full_101203-3-10"}],"textCenter":"(Se ve molesta, pero... Tengo que hacerlo...)"},{"chara":[{"cheek":0,"id":100102,"lipSynch":1,"mouthOpen":0,"voiceFull":"fullvoice/section_101203/vo_full_101203-3-12","voiceFullStop":"fullvoice/section_101203/vo_full_101203-3-11"}],"textCenter":"*Suspiro*"},{"chara":[{"cheek":0,"face":"mtn_ex_021.exp.json","id":100102,"motion":400,"mouthOpen":0,"voiceFull":"fullvoice/section_101203/vo_full_101203-3-13","voiceFullStop":"fullvoice/section_101203/vo_full_101203-3-12"}],"textCenter":"¡Puedo hacerlo!"},{"autoTurnLast":0.01,"chara":[{"cheek":1,"face":"mtn_ex_020.exp.json","id":100901,"motion":0,"mouthOpen":0,"pos":0},{"cheek":0,"face":"mtn_ex_050.exp.json","id":100102,"motion":0,"mouthOpen":0,"pos":2}],"turnChangeIn":"rollInFast","voiceFullStop":"fullvoice/section_101203/vo_full_101203-3-13"},{"bg":"bg_adv_21031.jpg","bgm":"bgm03_story02","chara":[{"id":100102,"voiceFull":"fullvoice/section_101203/vo_full_101203-3-14"}],"nameLeft":"Rena","nameRight":"Iroha","textRight":"U-um... ¡Rena!","turnChangeOut":"rollOutFast"},{"chara":[{"id":100901,"mouthOpen":0,"voiceFull":"fullvoice/section_101203/vo_full_101203-3-15","voiceFullStop":"fullvoice/section_101203/vo_full_101203-3-14"}],"textLeft":"¿Uh? ¿Quién eres?"},{"chara":[{"cheek":0,"face":"mtn_ex_050.exp.json","id":100901,"motion":400,"mouthOpen":0,"voiceFull":"fullvoice/section_101203/vo_full_101203-3-16","voiceFullStop":"fullvoice/section_101203/vo_full_101203-3-15"}],"textLeft":"[chara:100901:effect_emotion_surprise_0][se:7226_shock]Espera. ¡¿No eres la que@intentó pararme antes?!"},{"chara":[{"cheek":0,"face":"mtn_ex_020.exp.json","id":100901,"mouthOpen":0,"voiceFull":"fullvoice/section_101203/vo_full_101203-3-17","voiceFullStop":"fullvoice/section_101203/vo_full_101203-3-16"}],"textLeft":"...¿Qué es lo que quieres...?"},{"chara":[{"cheek":0,"id":100901,"motion":0,"mouthOpen":0,"voiceFull":"fullvoice/section_101203/vo_full_101203-3-18","voiceFullStop":"fullvoice/section_101203/vo_full_101203-3-17"}],"textLeft":"Si Momoko te mando aquí,@solo déjame sola por favor."},{"chara":[{"cheek":0,"face":"mtn_ex_030.exp.json","id":100102,"motion":200,"mouthOpen":0,"voiceFull":"fullvoice/section_101203/vo_full_101203-3-19","voiceFullStop":"fullvoice/section_101203/vo_full_101203-3-18"}],"textRight":"No, no es eso..."},{"chara":[{"cheek":1,"id":100901,"motion":200,"mouthOpen":0,"voiceFull":"fullvoice/section_101203/vo_full_101203-3-20","voiceFullStop":"fullvoice/section_101203/vo_full_101203-3-19"}],"textLeft":"¡¿Entonces que?!"},{"autoTurnFirst":1.0,"chara":[{"cheek":1,"face":"mtn_ex_050.exp.json","id":100102,"motion":400,"mouthOpen":0,"voiceFull":"fullvoice/section_101203/vo_full_101203-3-21","voiceFullStop":"fullvoice/section_101203/vo_full_101203-3-20"}],"enableSkipAutoTurn":1,"textRight":"Eek... Um..."},{"chara":[{"cheek":1,"face":"mtn_ex_030.exp.json","id":100102}]},{"chara":[{"cheek":0,"id":100102,"motion":0,"mouthOpen":0,"voiceFull":"fullvoice/section_101203/vo_full_101203-3-22","voiceFullStop":"fullvoice/section_101203/vo_full_101203-3-21"}],"enableSkipAutoTurn":0,"textRight":"En realidad escuché que te gusta Sayuki Fumino.@Te quería hablar sobre ella..."},{"chara":[{"cheek":0,"face":"mtn_ex_050.exp.json","id":100901,"motion":0,"mouthOpen":0,"voiceFull":"fullvoice/section_101203/vo_full_101203-3-23","voiceFullStop":"fullvoice/section_101203/vo_full_101203-3-22"}],"textLeft":"[chara:100901:effect_emotion_surprise_0][se:7226_shock]¿Uh? ¡¿La conoces también?!"},{"chara":[{"cheek":1,"face":"mtn_ex_010.exp.json","id":100901,"mouthOpen":0,"voiceFull":"fullvoice/section_101203/vo_full_101203-3-24","voiceFullStop":"fullvoice/section_101203/vo_full_101203-3-23"}],"textLeft":"[chara:100901:effect_emotion_joy_0][se:7222_happy]¡Sayuki Fumino!@¡Le encantan las espadas y la historia!"},{"chara":[{"cheek":0,"id":100102,"lipSynch":0,"mouthOpen":0,"voiceFull":"fullvoice/section_101203/vo_full_101203-3-25","voiceFullStop":"fullvoice/section_101203/vo_full_101203-3-24"}],"textRight":"(Ah, así que...es ese tipo de Idol...)"},{"chara":[{"cheek":0,"face":"mtn_ex_010.exp.json","id":100102,"lipSynch":1,"motion":100,"mouthOpen":0,"voiceFull":"fullvoice/section_101203/vo_full_101203-3-26","voiceFullStop":"fullvoice/section_101203/vo_full_101203-3-25"}],"textRight":"S-sí, y la cosa es que."},{"chara":[{"cheek":0,"id":100102,"mouthOpen":0,"voiceFull":"fullvoice/section_101203/vo_full_101203-3-27","voiceFullStop":"fullvoice/section_101203/vo_full_101203-3-26"}],"textRight":"Escuché que hará un show secreto en el lugar de@construcción abandonado en el Distrito Shinsei. "},{"chara":[{"cheek":0,"id":100102,"motion":200,"mouthOpen":0,"voiceFull":"fullvoice/section_101203/vo_full_101203-3-28","voiceFullStop":"fullvoice/section_101203/vo_full_101203-3-27"}],"textRight":"¿Me preguntaba si irías conmigo?"},{"chara":[{"cheek":1,"face":"mtn_ex_011.exp.json","id":100901,"motion":100,"mouthOpen":0,"voiceFull":"fullvoice/section_101203/vo_full_101203-3-29","voiceFullStop":"fullvoice/section_101203/vo_full_101203-3-28"}],"textLeft":"¡Claro que iré!"},{"chara":[{"cheek":1,"face":"mtn_ex_010.exp.json","id":100901,"mouthOpen":0,"voiceFull":"fullvoice/section_101203/vo_full_101203-3-30","voiceFullStop":"fullvoice/section_101203/vo_full_101203-3-29"}],"textLeft":"Entonces, ¿tienes tu glow stick de espada?"},{"chara":[{"cheek":0,"face":"mtn_ex_050.exp.json","id":100102,"motion":0,"mouthOpen":0,"voiceFull":"fullvoice/section_101203/vo_full_101203-3-31","voiceFullStop":"fullvoice/section_101203/vo_full_101203-3-30"}],"textRight":"Espada... Uh..."},{"chara":[{"cheek":0,"face":"mtn_ex_041.exp.json","id":100102,"mouthOpen":0,"voiceFull":"fullvoice/section_101203/vo_full_101203-3-32","voiceFullStop":"fullvoice/section_101203/vo_full_101203-3-31"}],"textRight":"¡S-sí!"},{"bgm":"stop","chara":[{"cheek":0,"face":"mtn_ex_020.exp.json","id":100901,"motion":201,"mouthOpen":0,"voiceFull":"fullvoice/section_101203/vo_full_101203-3-33","voiceFullStop":"fullvoice/section_101203/vo_full_101203-3-32"}],"textLeft":"¡Muy mal que no exista tal cosa!"},{"chara":[{"cheek":0,"face":"mtn_ex_050.exp.json","id":100102,"motion":401,"mouthOpen":0,"voiceFull":"fullvoice/section_101203/vo_full_101203-3-34","voiceFullStop":"fullvoice/section_101203/vo_full_101203-3-33"}],"textRight":"[chara:100102:effect_emotion_surprise_0][se:7226_shock]¡¿Qué?!"},{"bgm":"bgm01_battle04","chara":[{"cheek":0,"id":100901,"motion":0,"mouthOpen":0,"voiceFull":"fullvoice/section_101203/vo_full_101203-3-35","voiceFullStop":"fullvoice/section_101203/vo_full_101203-3-34"}],"textLeft":"Justo como pensé.@Momoko te habló de eso, ¿verdad?"},{"chara":[{"cheek":0,"face":"mtn_ex_020.exp.json","id":100901,"motion":200,"mouthOpen":0,"voiceFull":"fullvoice/section_101203/vo_full_101203-3-36","voiceFullStop":"fullvoice/section_101203/vo_full_101203-3-35"}],"textLeft":"Que bonito, intentando engañarme con@una de mis idols favoritas."},{"chara":[{"cheek":0,"id":100901,"mouthOpen":0,"voiceFull":"fullvoice/section_101203/vo_full_101203-3-37","voiceFullStop":"fullvoice/section_101203/vo_full_101203-3-36"}],"textLeft":"Eres lo peor."},{"chara":[{"cheek":1,"id":100901,"motion":201,"mouthOpen":0,"voiceFull":"fullvoice/section_101203/vo_full_101203-3-38","voiceFullStop":"fullvoice/section_101203/vo_full_101203-3-37"}],"textLeft":"¡En serio, solo déjame sola!@No hay forma de que vaya contigo."},{"chara":[{"cheek":0,"face":"mtn_ex_030.exp.json","id":100102,"motion":200,"mouthOpen":0,"voiceFull":"fullvoice/section_101203/vo_full_101203-3-39","voiceFullStop":"fullvoice/section_101203/vo_full_101203-3-38"}],"textRight":"Ugh... Um, pero..."},{"chara":[{"id":100901,"motion":200,"mouthOpen":0,"voiceFull":"fullvoice/section_101203/vo_full_101203-3-40","voiceFullStop":"fullvoice/section_101203/vo_full_101203-3-39"}],"textLeft":"¿Qué?@¿Acaso buscas pelear?"},{"chara":[{"cheek":0,"id":100102,"mouthOpen":0,"voiceFull":"fullvoice/section_101203/vo_full_101203-3-41","voiceFullStop":"fullvoice/section_101203/vo_full_101203-3-40"}],"textRight":"Lo siento..."},{"chara":[{"cheek":0,"id":100901,"motion":201,"mouthOpen":0,"voiceFull":"fullvoice/section_101203/vo_full_101203-3-42","voiceFullStop":"fullvoice/section_101203/vo_full_101203-3-41"}],"textLeft":"Si sientes que necesitas disculparte,@no lo hagas en primer lugar, ¡idiota!"},{"chara":[{"cheek":0,"id":100102,"motion":301,"mouthOpen":0,"voiceFull":"fullvoice/section_101203/vo_full_101203-3-43","voiceFullStop":"fullvoice/section_101203/vo_full_101203-3-42"}],"textRight":"[chara:100102:effect_emotion_sad_0][se:7224_fall_into]Uh..."},{"bgm":"stop","nameCenter":"","textBg":"shout","textCenter":"¡Rena!","voiceFull":"fullvoice/section_101203/vo_full_101203-3-44"},{"chara":[{"cheek":0,"face":"mtn_ex_050.exp.json","id":100901,"motion":0,"mouthOpen":0,"voiceFull":"fullvoice/section_101203/vo_full_101203-3-45","voiceFullStop":"fullvoice/section_101203/vo_full_101203-3-44"}],"textLeft":"¡¿Ahora quién es?!"},{"autoTurnLast":0.5,"chara":[{"cheek":0,"face":"mtn_ex_020.exp.json","id":101101,"motion":0,"mouthOpen":0,"pos":2,"voiceFullStop":"fullvoice/section_101203/vo_full_101203-3-45"}]},{"autoTurnFirst":1.0,"chara":[{"cheek":0,"face":"mtn_ex_030.exp.json","id":100901,"voiceFull":"fullvoice/section_101203/vo_full_101203-3-46"}],"enableSkipAutoTurn":1,"textLeft":"[chara:100901:effect_emotion_surprise_0][se:7226_shock]*Susto*@Tu... Kaede..."},{"chara":[{"cheek":0,"id":100901,"motion":0,"mouthOpen":0}]},{"chara":[{"cheek":0,"face":"mtn_ex_030.exp.json","id":100102,"motion":0,"mouthOpen":0,"pos":0,"voiceFull":"fullvoice/section_101203/vo_full_101203-3-47","voiceFullStop":"fullvoice/section_101203/vo_full_101203-3-46"}],"enableSkipAutoTurn":0,"nameLeft":"Iroha","textLeft":"¿Kaede...?@¿Por qué estás aquí?"},{"autoTurnLast":2.0,"turnChangeIn":"fadeIn","voiceFullStop":"fullvoice/section_101203/vo_full_101203-3-47"}]},"version":3}