{
    "story": {
        "group_1": [
            {
                "autoTurnLast": 0.01,
                "bg": "bg_adv_19252.jpg",
                "chara": [
                    {
                        "cheek": 0,
                        "face": "mtn_ex_050.exp.json",
                        "id": 100702,
                        "motion": 0,
                        "pos": 0,
                        "soulGem": 0
                    },
                    {
                        "id": 810000,
                        "pos": 2,
                        "posX": 40,
                        "posY": 0
                    }
                ],
                "turnChangeIn": "fadeIn"
            },
            {
                "bgm": "bgm03_story13",
                "chara": [
                    {
                        "id": 100702,
                        "voiceFull": "fullvoice/section_102003/vo_full_102003-5-1"
                    }
                ],
                "nameLeft": "Touka",
                "nameRight": "Kyubey",
                "textLeft": "Tú eres Kyubey, ¿no es así?",
                "turnChangeOut": "fadeOut"
            },
            {
                "textRight": "Ha pasado algún tiempo, Touka Satomi.",
                "voiceFull": "fullvoice/section_102003/vo_full_102003-5-2",
                "voiceFullStop": "fullvoice/section_102003/vo_full_102003-5-1"
            },
            {
                "chara": [
                    {
                        "cheek": 0,
                        "face": "mtn_ex_010.exp.json",
                        "id": 100702,
                        "motion": 100,
                        "voiceFull": "fullvoice/section_102003/vo_full_102003-5-3",
                        "voiceFullStop": "fullvoice/section_102003/vo_full_102003-5-2"
                    }
                ],
                "textLeft": "*Risilla* ¡No te he visto de desde que mi Hermana@Mayor apareció en ese Laberinto!"
            },
            {
                "textRight": "¿Hermana Mayor?",
                "voiceFull": "fullvoice/section_102003/vo_full_102003-5-4",
                "voiceFullStop": "fullvoice/section_102003/vo_full_102003-5-3"
            },
            {
                "textRight": "¿Te refieres a una chica nacida antes que tú,@de la misma madre...?",
                "voiceFull": "fullvoice/section_102003/vo_full_102003-5-5",
                "voiceFullStop": "fullvoice/section_102003/vo_full_102003-5-4"
            },
            {
                "chara": [
                    {
                        "id": 100702,
                        "motion": 200,
                        "voiceFull": "fullvoice/section_102003/vo_full_102003-5-6",
                        "voiceFullStop": "fullvoice/section_102003/vo_full_102003-5-5"
                    }
                ],
                "textLeft": "No, no, no seas tan literal.@¡Me refiero a Iroha Tamaki!"
            },
            {
                "textRight": "Ya veo. Iroha Tamaki es una de tus@conocidas.",
                "voiceFull": "fullvoice/section_102003/vo_full_102003-5-7",
                "voiceFullStop": "fullvoice/section_102003/vo_full_102003-5-6"
            },
            {
                "textRight": "Ahora entiendo.",
                "voiceFull": "fullvoice/section_102003/vo_full_102003-5-8",
                "voiceFullStop": "fullvoice/section_102003/vo_full_102003-5-7"
            },
            {
                "chara": [
                    {
                        "id": 100702,
                        "motion": 1,
                        "voiceFull": "fullvoice/section_102003/vo_full_102003-5-9",
                        "voiceFullStop": "fullvoice/section_102003/vo_full_102003-5-8"
                    }
                ],
                "textLeft": "Suficiente de eso, ¡solo hay una razón por la@que te mostrarías ante mí!"
            },
            {
                "chara": [
                    {
                        "id": 100702,
                        "voiceFull": "fullvoice/section_102003/vo_full_102003-5-10",
                        "voiceFullStop": "fullvoice/section_102003/vo_full_102003-5-9"
                    }
                ],
                "textLeft": "Viniste para decirme que estoy calificada para@ser una Chica Mágica, ¿verdad?"
            },
            {
                "textRight": "Sí. Me alegro que entiendas rápido.",
                "voiceFull": "fullvoice/section_102003/vo_full_102003-5-11",
                "voiceFullStop": "fullvoice/section_102003/vo_full_102003-5-10"
            },
            {
                "textRight": "Puedo concederte cualquier deseo que@tengas.",
                "voiceFull": "fullvoice/section_102003/vo_full_102003-5-12",
                "voiceFullStop": "fullvoice/section_102003/vo_full_102003-5-11"
            },
            {
                "chara": [
                    {
                        "cheek": 0,
                        "face": "mtn_ex_050.exp.json",
                        "id": 100702,
                        "motion": 400,
                        "voiceFull": "fullvoice/section_102003/vo_full_102003-5-13",
                        "voiceFullStop": "fullvoice/section_102003/vo_full_102003-5-12"
                    }
                ],
                "textLeft": "Quiero que me digas algo primero. ¡Muchas cosas,@de hecho!"
            },
            {
                "textRight": "¿Qué te gustaría saber?",
                "voiceFull": "fullvoice/section_102003/vo_full_102003-5-14",
                "voiceFullStop": "fullvoice/section_102003/vo_full_102003-5-13"
            },
            {
                "chara": [
                    {
                        "cheek": 0,
                        "face": "mtn_ex_010.exp.json",
                        "id": 100702,
                        "motion": 0,
                        "voiceFull": "fullvoice/section_102003/vo_full_102003-5-15",
                        "voiceFullStop": "fullvoice/section_102003/vo_full_102003-5-14"
                    }
                ],
                "textLeft": "No tienes que hablar. Simplemente le@preguntaré a tu red."
            },
            {
                "textRight": "¿Mi red?",
                "voiceFull": "fullvoice/section_102003/vo_full_102003-5-16",
                "voiceFullStop": "fullvoice/section_102003/vo_full_102003-5-15"
            },
            {
                "chara": [
                    {
                        "id": 100702,
                        "voiceFull": "fullvoice/section_102003/vo_full_102003-5-17",
                        "voiceFullStop": "fullvoice/section_102003/vo_full_102003-5-16"
                    }
                ],
                "textLeft": "Sí. Tu red."
            },
            {
                "textRight": "Touka Satomi... ¡¿Qué estás―",
                "voiceFull": "fullvoice/section_102003/vo_full_102003-5-18",
                "voiceFullStop": "fullvoice/section_102003/vo_full_102003-5-17"
            },
            {
                "textRight": "...?!",
                "voiceFull": "fullvoice/section_102003/vo_full_102003-5-19",
                "voiceFullStop": "fullvoice/section_102003/vo_full_102003-5-18"
            },
            {
                "chara": [
                    {
                        "cheek": 0,
                        "face": "mtn_ex_011.exp.json",
                        "id": 100702,
                        "motion": 100,
                        "voiceFull": "fullvoice/section_102003/vo_full_102003-5-20",
                        "voiceFullStop": "fullvoice/section_102003/vo_full_102003-5-19"
                    }
                ],
                "textLeft": "*Risilla*"
            },
            {
                "autoTurnLast": 2,
                "flashEffect": "flashWhiteSlow2",
                "se": "7211_souljem_02",
                "textClear": 1,
                "voiceFullStop": "fullvoice/section_102003/vo_full_102003-5-20"
            },
            {
                "textRight": "Esta habitación tuya...",
                "voiceFull": "fullvoice/section_102003/vo_full_102003-5-21"
            },
            {
                "textRight": "¿Realmente estás intentando entrar en mi@cabeza?",
                "voiceFull": "fullvoice/section_102003/vo_full_102003-5-22",
                "voiceFullStop": "fullvoice/section_102003/vo_full_102003-5-21"
            },
            {
                "chara": [
                    {
                        "cheek": 0,
                        "face": "mtn_ex_010.exp.json",
                        "id": 100702,
                        "motion": 0,
                        "voiceFull": "fullvoice/section_102003/vo_full_102003-5-23",
                        "voiceFullStop": "fullvoice/section_102003/vo_full_102003-5-22"
                    }
                ],
                "textLeft": "Tu conciencia está siendo replicada,@¿verdad?"
            },
            {
                "chara": [
                    {
                        "id": 100702,
                        "motion": 201,
                        "voiceFull": "fullvoice/section_102003/vo_full_102003-5-24",
                        "voiceFullStop": "fullvoice/section_102003/vo_full_102003-5-23"
                    }
                ],
                "textLeft": "Así se me hace mucho más rápido buscar en la@red integrada de la que eres parte."
            },
            {
                "chara": [
                    {
                        "effect": "fadeout",
                        "id": 810000
                    }
                ],
                "textBg": "shout",
                "textRight": "[flashEffect:flashWhite2][bgEffect:shakeLarge]¡Kyu!",
                "voiceFull": "fullvoice/section_102003/vo_full_102003-5-25",
                "voiceFullStop": "fullvoice/section_102003/vo_full_102003-5-24"
            },
            {
                "chara": [
                    {
                        "cheek": 0,
                        "face": "mtn_ex_050.exp.json",
                        "id": 100702,
                        "motion": 0,
                        "voiceFull": "fullvoice/section_102003/vo_full_102003-5-26",
                        "voiceFullStop": "fullvoice/section_102003/vo_full_102003-5-25"
                    }
                ],
                "textLeft": "¡Uups! Se escapó..."
            },
            {
                "autoTurnLast": 1,
                "item": [
                    {
                        "path": "resource/scenario/img/chapter10/102003_qb_silhouette.png",
                        "posX": 270,
                        "posY": -19,
                        "visible": "appear"
                    }
                ],
                "textClear": 1,
                "voiceFullStop": "fullvoice/section_102003/vo_full_102003-5-26"
            },
            {
                "textRight": "No estaba huyendo.",
                "voiceFull": "fullvoice/section_102003/vo_full_102003-5-27",
                "voiceFullStop": "fullvoice/section_102003/vo_full_102003-5-26"
            },
            {
                "textRight": "Considerando la enorme diferencia entre@nuestras civilizaciones...",
                "voiceFull": "fullvoice/section_102003/vo_full_102003-5-28",
                "voiceFullStop": "fullvoice/section_102003/vo_full_102003-5-27"
            },
            {
                "textRight": "No hay forma de que tus máquinas hubieran@salido ilesas de eso.",
                "voiceFull": "fullvoice/section_102003/vo_full_102003-5-29",
                "voiceFullStop": "fullvoice/section_102003/vo_full_102003-5-28"
            },
            {
                "textRight": "Para ser franco, deberías agradecerme por@haber cortado esa conexión.",
                "voiceFull": "fullvoice/section_102003/vo_full_102003-5-30",
                "voiceFullStop": "fullvoice/section_102003/vo_full_102003-5-29"
            },
            {
                "chara": [
                    {
                        "cheek": 0,
                        "face": "mtn_ex_030.exp.json",
                        "id": 100702,
                        "motion": 300,
                        "voiceFull": "fullvoice/section_102003/vo_full_102003-5-31",
                        "voiceFullStop": "fullvoice/section_102003/vo_full_102003-5-30"
                    }
                ],
                "textLeft": "Ya veo..."
            },
            {
                "textRight": "Ahora, Touka Satomi.",
                "voiceFull": "fullvoice/section_102003/vo_full_102003-5-32",
                "voiceFullStop": "fullvoice/section_102003/vo_full_102003-5-31"
            },
            {
                "chara": [
                    {
                        "cheek": 0,
                        "face": "mtn_ex_050.exp.json",
                        "id": 100702,
                        "motion": 0,
                        "voiceFull": "fullvoice/section_102003/vo_full_102003-5-33",
                        "voiceFullStop": "fullvoice/section_102003/vo_full_102003-5-32"
                    }
                ],
                "textLeft": "¿Sí?"
            },
            {
                "textRight": "¿Harás un contrato conmigo, para convertirte@en una Chica Mágica?",
                "voiceFull": "fullvoice/section_102003/vo_full_102003-5-34",
                "voiceFullStop": "fullvoice/section_102003/vo_full_102003-5-33"
            },
            {
                "chara": [
                    {
                        "cheek": 0,
                        "face": "mtn_ex_010.exp.json",
                        "id": 100702,
                        "motion": 200,
                        "voiceFull": "fullvoice/section_102003/vo_full_102003-5-35",
                        "voiceFullStop": "fullvoice/section_102003/vo_full_102003-5-34"
                    }
                ],
                "textLeft": "Lo consideraré... después de que me digas@las cosas que quiero saber."
            },
            {
                "chara": [
                    {
                        "cheek": 0,
                        "face": "mtn_ex_030.exp.json",
                        "id": 100702,
                        "voiceFull": "fullvoice/section_102003/vo_full_102003-5-36",
                        "voiceFullStop": "fullvoice/section_102003/vo_full_102003-5-35"
                    }
                ],
                "textLeft": "Es una pena que tengamos que hablar, pero@bueno..."
            },
            {
                "textRight": "No me molesta.",
                "voiceFull": "fullvoice/section_102003/vo_full_102003-5-37",
                "voiceFullStop": "fullvoice/section_102003/vo_full_102003-5-36"
            },
            {
                "textRight": "No tengo nada que ocultarte.",
                "voiceFull": "fullvoice/section_102003/vo_full_102003-5-38",
                "voiceFullStop": "fullvoice/section_102003/vo_full_102003-5-37"
            },
            {
                "textRight": "Pregunta, y yo te responderé.",
                "voiceFull": "fullvoice/section_102003/vo_full_102003-5-39",
                "voiceFullStop": "fullvoice/section_102003/vo_full_102003-5-38"
            },
            {
                "autoTurnLast": 0.01,
                "turnChangeIn": "fadeIn",
                "voiceFullStop": "fullvoice/section_102003/vo_full_102003-5-39"
            }
        ]
    },
    "version": 3
}