{"story":{"group_1":[{"bg":"bg_adv_12065.jpg","bgm":"stop","chara":[{"cheek":0,"face":"mtn_ex_020.exp.json","id":100301,"motion":0,"pos":0},{"cheek":0,"face":"mtn_ex_020.exp.json","id":300601,"motion":0,"pos":2}],"nameNarration":"","narration":"＜El Torneo de Hanetsuki del Santuario de Mizuna@volvió después de muchos años.＞","narrationBg":"bg_adv_12065.jpg","narrationEffect":"in","turnChangeIn":"fadeIn","turnChangeOut":"fadeOut"},{"narration":"＜¡En este torneo, el equipo que gane@primero 5 puntos pasa a la siguiente ronda!＞"},{"narration":"＜Y así, comenzaron@los enfrentamientos...＞"},{"bgm":"bgm01_battle02","chara":[{"id":100301,"motion":201}],"nameLeft":"Tsuruno","nameRight":"Emiri","narrationEffect":"out","textLeft":"[flashEffect:flashWhite2][se:4141_jumping]¡Hyaaagh!"},{"chara":[{"cheek":0,"face":"mtn_ex_020.exp.json","id":300601,"motion":200}],"textRight":"¡Es todo tuyo, Princesa Ria!"},{"chara":[{"cheek":0,"face":"mtn_ex_020.exp.json","id":301001,"motion":1,"pos":2}],"nameRight":"Ria","textRight":"¡Déjamelo a mí!"},{"chara":[{"eyeClose":1,"id":301001}],"textRight":"¡Contemplen! El magnífico..."},{"chara":[{"eyeClose":0,"id":301001,"motion":200}],"textRight":"[flashEffect:flashWhite2]... ¡golpe de Ria Ami...!"},{"chara":[{"cheek":0,"face":"mtn_ex_050.exp.json","id":100101,"motion":401,"pos":0}],"nameLeft":"Iroha","textLeft":"¡Falló!"},{"chara":[{"cheek":1,"face":"mtn_ex_050.exp.json","id":301001,"motion":400}],"textRight":"¡Nooo!"},{"chara":[{"cheek":0,"face":"mtn_ex_020.exp.json","id":801400,"motion":0,"pos":1}],"nameCenter":"","textCenter":"¡Un punto!@... ¡Y con ese son 5!"},{"chara":[{"cheek":0,"face":"mtn_ex_011.exp.json","id":100101,"motion":400},{"effect":"fadeout","id":801400},{"id":301001,"motion":0}],"textLeft":"¡Woo hoo!"},{"chara":[{"cheek":0,"face":"mtn_ex_030.exp.json","id":300601,"motion":0,"pos":0}],"nameLeft":"Emiri","textLeft":"Ahhh, Princesa Ria..."},{"chara":[{"cheek":0,"face":"mtn_ex_011.exp.json","id":300601,"motion":100}],"textLeft":"No te preocupes, ¿sí?"},{"chara":[{"cheek":1,"face":"mtn_ex_030.exp.json","id":301001,"motion":300}],"textRight":"Emily..."},{"chara":[{"cheek":0,"face":"mtn_ex_010.exp.json","id":100301,"motion":100,"pos":0}],"nameLeft":"Tsuruno","textLeft":"Sí, fue un partido reñido..."},{"chara":[{"cheek":0,"face":"mtn_ex_011.exp.json","id":100301}],"textLeft":"... ¡Princesa Pita!"},{"chara":[{"cheek":1,"face":"mtn_ex_020.exp.json","id":301001,"motion":400}],"textRight":"¿¡Pita!? ¡Yo no hago kebabs!"},{"autoTurnLast":0.01,"chara":[{"cheek":0,"face":"mtn_ex_010.exp.json","id":100401,"motion":0,"pos":1}],"turnChangeIn":"rollInFast"},{"chara":[{"id":100401,"motion":400}],"nameCenter":"Sana","textCenter":"¡Ganaron!","turnChangeOut":"rollOutFast"},{"autoTurnLast":0.2,"chara":[{"effect":"fadeout","id":100401}]},{"chara":[{"cheek":0,"face":"mtn_ex_010.exp.json","id":200350,"motion":100,"pos":0},{"cheek":0,"face":"mtn_ex_010.exp.json","id":210000,"motion":0,"pos":2}],"nameLeft":"Homura","nameRight":"Madoka","textLeft":"¡Iroha! ¡Tsuruno! ¡Buen trabajo!"},{"chara":[{"id":210000,"motion":100}],"textRight":"¡Sí! Y esto significa..."},{"nameNarration":"","narration":"＜¡Iroha y Tsuruno@están en las semifinales!＞","narrationBg":"bg_adv_12065.jpg","narrationEffect":"in"},{"autoTurnLast":0.01,"chara":[{"cheek":0,"face":"mtn_ex_020.exp.json","id":300101,"motion":0,"pos":0},{"cheek":0,"face":"mtn_ex_020.exp.json","id":302801,"motion":0,"pos":2}],"narrationEffect":"out","turnChangeIn":"fadeIn"},{"chara":[{"id":302801,"motion":200}],"nameLeft":"Kanoko","nameRight":"Ayame","textRight":"¡Termina esto, Felicia!","turnChangeOut":"fadeOut"},{"chara":[{"cheek":0,"face":"mtn_ex_020.exp.json","id":100501,"motion":0,"pos":2}],"nameRight":"Felicia","textRight":"¡Lo tengo!"},{"chara":[{"id":100501,"motion":200,"mouthOpen":1}],"textBg":"shout","textRight":"[flashEffect:flashWhite2][bgEffect:shakeSmall][se:4061_landing_jump5]!Toooma esto¡"},{"chara":[{"cheek":0,"eyeClose":1,"face":"mtn_ex_020.exp.json","id":300101,"motion":400,"mouthOpen":1}],"textLeft":"[flashEffect:flashRed2][se:3001_chara_damage][bgEffect:shakeSmall][chara:300101:effect_shake]¡Gah!"},{"chara":[{"cheek":0,"face":"mtn_ex_050.exp.json","id":302001,"motion":400,"pos":0}],"nameLeft":"Himika","textLeft":"¡Uff! ¡Justo en la frente!"},{"autoTurnLast":0.01,"chara":[{"cheek":0,"face":"mtn_ex_001.exp.json","id":302601,"motion":0,"pos":0},{"cheek":0,"face":"mtn_ex_010.exp.json","id":302701,"motion":0,"pos":2}],"turnChangeIn":"rollInFast"},{"chara":[{"cheek":0,"face":"mtn_ex_011.exp.json","id":302701,"motion":100}],"nameLeft":"Konoha","nameRight":"Hazuki","textRight":"¡Oh, Ayame y Felicia ganaron!","turnChangeOut":"rollOutFast"},{"chara":[{"id":302601,"motion":100}],"textLeft":"Nada mal..."},{"chara":[{"cheek":0,"face":"mtn_ex_010.exp.json","id":302601,"lipSynch":0}],"textLeft":"(¡Felicia es increíble!@¡Y sé que tú también puedes hacerlo, Ayame!)","turnEffect":"thinking"},{"chara":[{"cheek":0,"face":"mtn_ex_010.exp.json","id":302801,"motion":0,"pos":0},{"cheek":0,"face":"mtn_ex_010.exp.json","id":100501,"motion":0,"pos":2}],"nameNarration":"","narration":"＜¡Felicia y Ayame también@pasaron a las semifinales!＞","narrationBg":"bg_adv_12065.jpg","narrationEffect":"in","turnEffect":"stop"},{"chara":[{"id":100501,"motion":200}],"nameLeft":"Ayame","nameRight":"Felicia","narrationEffect":"out","textRight":"¡Así que ahora nos enfrentamos@a Iroha y Tsuruno!"},{"chara":[{"id":302801,"motion":100}],"textLeft":"¡No vamos a perder!"},{"chara":[{"cheek":0,"face":"mtn_ex_020.exp.json","id":100101,"motion":0,"pos":0},{"cheek":0,"face":"mtn_ex_001.exp.json","id":100301,"motion":200,"pos":2}],"nameLeft":"Iroha","nameRight":"Tsuruno","textRight":"¡Vamos a por ello, Iroha!"},{"chara":[{"id":100101,"motion":400}],"textLeft":"¡Sí!"},{"chara":[{"cheek":0,"face":"mtn_ex_030.exp.json","id":301901,"motion":0,"pos":0},{"cheek":0,"face":"mtn_ex_030.exp.json","id":300701,"motion":0,"pos":2}],"nameNarration":"","narration":"＜Y...＞","narrationBg":"bg_adv_12065.jpg","narrationEffect":"in"},{"chara":[{"id":301901}],"nameLeft":"Ayaka","nameRight":"Shizuku","narrationEffect":"out","textLeft":"Perdimos..."},{"chara":[{"cheek":0,"face":"mtn_ex_001.exp.json","id":301901,"motion":100}],"textLeft":"¡Eh, al menos déjame contar un chiste!@Un jugador de hanetsuki va al médico..."},{"chara":[{"id":300701,"motion":200}],"textRight":"No creo que eso ayude."},{"chara":[{"cheek":0,"face":"mtn_ex_001.exp.json","id":301201,"motion":100,"pos":0},{"cheek":0,"face":"mtn_ex_020.exp.json","id":300801,"motion":0,"pos":2}],"nameLeft":"Meiyui","nameRight":"Akira","textLeft":"Dos partidas más."},{"chara":[{"id":300801,"motion":100}],"textRight":"¡Sí! ¡Mantengámonos enfocadas!"},{"chara":[{"cheek":0,"face":"mtn_ex_050.exp.json","id":300401,"motion":0,"pos":0},{"cheek":0,"face":"mtn_ex_030.exp.json","id":101301,"motion":300,"pos":2}],"nameNarration":"","narration":"＜Las semifinalistas fueron...＞","narrationBg":"bg_adv_12065.jpg","narrationEffect":"in"},{"chara":[{"id":300401,"motion":400,"mouthOpen":0}],"nameLeft":"Sasara","nameRight":"Asuka","narrationEffect":"out","textLeft":"¡Nooo! ¡No pude hacerlo!"},{"chara":[{"cheek":1,"id":101301,"tear":1}],"textRight":"*Llanto*"},{"chara":[{"id":101301,"motion":200}],"textRight":"¡Muy bien, debo matarme!"},{"chara":[{"cheek":0,"face":"mtn_ex_020.exp.json","id":300401,"motion":200}],"textLeft":"¡No empieces así el año!"},{"chara":[{"cheek":0,"face":"mtn_ex_020.exp.json","id":100901,"motion":100,"pos":0},{"cheek":0,"face":"mtn_ex_020.exp.json","id":101001,"motion":0,"pos":2}],"nameLeft":"Rena","nameRight":"Momoko","textLeft":"¡Ganamos!"},{"chara":[{"id":101001,"lipSynch":0,"motion":0}],"textRight":"..."},{"chara":[{"id":101001,"motion":200}],"textRight":"¡Ahora es cuando las cosas@realmente empiezan, Rena!"},{"nameNarration":"","narration":"＜¡Y de este modo,@las semifinalistas quedaron decididas!＞","narrationBg":"bg_adv_12065.jpg","narrationEffect":"in"},{"autoTurnLast":2.0,"narrationEffect":"out","turnChangeIn":"fadeIn"}]},"version":3}